moesifwsgi/__init__.py
moesifwsgi/client_ip.py
moesifwsgi/event_mapper.py
moesifwsgi/http_response_catcher.py
moesifwsgi/logger_helper.py
moesifwsgi/middleware.py
moesifwsgi/moesif_data_holder.py
moesifwsgi/regex_config_helper.py
moesifwsgi/workers.py
moesifwsgi-1.10.4.dist-info/licenses/LICENSE
moesifwsgi-1.10.4.dist-info/METADATA
moesifwsgi-1.10.4.dist-info/WHEEL
moesifwsgi-1.10.4.dist-info/top_level.txt
moesifwsgi-1.10.4.dist-info/RECORD
