Metadata-Version: 2.4
Name: moesifwsgi
Version: 1.10.4
Summary: Moesif Middleware for Python WSGI based platforms (Flask, Bottle & Others)
Home-page: https://www.moesif.com/docs/server-integration/python-wsgi/
Author: Moesif, Inc
Author-email: team@moesif.com
License: Apache Software License
Keywords: log analysis restful api development debug wsgi flask bottle http middleware
Classifier: Development Status :: 5 - Production/Stable
Classifier: Intended Audience :: Developers
Classifier: Topic :: Internet :: Log Analysis
Classifier: Topic :: Software Development :: Debuggers
Classifier: Topic :: Software Development :: Libraries
Classifier: Topic :: Internet :: WWW/HTTP
Classifier: License :: OSI Approved :: Apache Software License
Classifier: Programming Language :: Python :: 2
Classifier: Programming Language :: Python :: 2.7
Classifier: Programming Language :: Python :: 3
Classifier: Programming Language :: Python :: 3.3
Classifier: Programming Language :: Python :: 3.4
Classifier: Programming Language :: Python :: 3.5
Classifier: Programming Language :: Python :: 3.6
Classifier: Programming Language :: Python :: 3.7
Classifier: Programming Language :: Python :: 3.8
Classifier: Programming Language :: Python :: 3.9
Classifier: Programming Language :: Python :: 3.10
Classifier: Programming Language :: Python :: 3.11
License-File: LICENSE
Requires-Dist: requests>=2.30.0
Requires-Dist: isodatetimehandler>=1.0.2
Requires-Dist: moesifapi>=1.5.5
Requires-Dist: moesifpythonrequest>=0.3.5
Requires-Dist: readerwriterlock>=1.0.9
Requires-Dist: apscheduler>=3.10.4
Provides-Extra: dev
Provides-Extra: test
Requires-Dist: nose; extra == "test"
Dynamic: author
Dynamic: author-email
Dynamic: classifier
Dynamic: description
Dynamic: description-content-type
Dynamic: home-page
Dynamic: keywords
Dynamic: license
Dynamic: license-file
Dynamic: provides-extra
Dynamic: requires-dist
Dynamic: summary
